<SpecialEvents>
	<MasterList>
		<DataID id="187000" name="AnimalFriendlyThanksgiving" />
		<DataID id="187001" name="AnimalFriendlyThanksgiving_Store" onDeprecated="delete" endDate="AFT_End" />
	</MasterList>
	<SpecialEvent id="187000" name="AnimalFriendlyThanksgiving">
		<Variable name="AFT_PreExpiryDisplayed24" value="false" />
		<Variable name="AFT_PreExpiryDisplayed72" value="false" />
		<Variable name="AFT_ExpiryDisplayed" value="false" />
		<Variable name="AFT_IntroSeen" value="false" />
		<onExit destroyHUD="true" />
		<SpecialButtons>
			<Button mode="game" icon="ICO_CUR_AnimalFriendlyThanksgiving_CurrencyActivistBadge_LG">
				<Requirements>
					<Requirement type="land" land="Springfield" />
					<Requirement type="variable" variable="AFT_IntroSeen" />
					<Requirement type="variable" variable="AFT_Complete" not="true" />
					<Requirement type="time" end="AFT_End" />
				</Requirements>
				<RunScript>
					<Script name="OpenMasterQuest" package="AFT_Scripts" />
				</RunScript>
			</Button>
		</SpecialButtons>
		<EventCurrencyJobLists>
			<JobList name="AFT_JL_01">
				<Title value="QST_ThisThanksgivingsGoneToTheBirds_1_1_name" />
				<ResourceGenerator resourceCapSelector="__AFT_GameConfig:ResourceQuantities:ResourceList01__" slotsUnlockedVariable="Monorail_UnusedVariable" resourceName="AFT_ActivistBadges" resourceCapIcon="ico_mono15_junk_sm.rgb" topupConfig="AFT_Ratio" menuConfig="AFT_MenuConfig:ResourceGeneratorConfig">
					<Slot>
						<Job name="OptimizeTofunWithCONRAD" character="QuinnHopper" />
					</Slot>
					<Slot>
						<Job name="SubOutSpaghettiWithZucchini" character="Luigi" />
					</Slot>
					<Slot>
						<Job name="SubstituteCafeteriaMysteryMeat" character="Lisa" />
					</Slot>
					<Slot>
						<Job name="SubMeatWithGardenVeggies" character="Ned" />
					</Slot>
					<Slot>
						<Job name="CutBeefToCutCosts" character="Krusty" />
					</Slot>
					<Slot>
						<Job name="SubstituteMothersPackedLunch" character="Skinner" />
					</Slot>
					<Slot>
						<Job name="EatVeggiesCompetitively" character="CBGuy" />
					</Slot>
					<Slot>
						<Job name="PreachHolyVeganism" character="Lovejoy" />
					</Slot>
				</ResourceGenerator>
			</JobList>
			<JobList name="AFT_JL_02">
				<Title value="QST_ThisThanksgivingsGoneToTheBirds_2_1_name" />
				<ResourceGenerator resourceCapSelector="__AFT_GameConfig:ResourceQuantities:ResourceList02__" slotsUnlockedVariable="Monorail_UnusedVariable" resourceName="AFT_ActivistBadges" resourceCapIcon="ico_mono15_junk_sm.rgb" topupConfig="AFT_Ratio" menuConfig="AFT_MenuConfig:ResourceGeneratorConfig">
					<Slot>
						<Job name="OptimizeTofunWithCONRAD" character="QuinnHopper" />
					</Slot>
					<Slot>
						<Job name="SubOutSpaghettiWithZucchini" character="Luigi" />
					</Slot>
					<Slot>
						<Job name="SubstituteCafeteriaMysteryMeat" character="Lisa" />
					</Slot>
					<Slot>
						<Job name="SubMeatWithGardenVeggies" character="Ned" />
					</Slot>
					<Slot>
						<Job name="CutBeefToCutCosts" character="Krusty" />
					</Slot>
					<Slot>
						<Job name="SubstituteMothersPackedLunch" character="Skinner" />
					</Slot>
					<Slot>
						<Job name="EatVeggiesCompetitively" character="CBGuy" />
					</Slot>
					<Slot>
						<Job name="PreachHolyVeganism" character="Lovejoy" />
					</Slot>
				</ResourceGenerator>
			</JobList>
			<JobList name="AFT_JL_03">
				<Title value="QST_ThisThanksgivingsGoneToTheBirds_3_1_name" />
				<ResourceGenerator resourceCapSelector="__AFT_GameConfig:ResourceQuantities:ResourceList03__" slotsUnlockedVariable="Monorail_UnusedVariable" resourceName="AFT_ActivistBadges" resourceCapIcon="ico_mono15_junk_sm.rgb" topupConfig="AFT_Ratio" menuConfig="AFT_MenuConfig:ResourceGeneratorConfig">
					<Slot>
						<Job name="OptimizeTofunWithCONRAD" character="QuinnHopper" />
					</Slot>
					<Slot>
						<Job name="SubOutSpaghettiWithZucchini" character="Luigi" />
					</Slot>
					<Slot>
						<Job name="RegressTofunBugs" character="Lisa" skin="ProgrammerLisa" />
					</Slot>
					<Slot>
						<Job name="SubMeatWithGardenVeggies" character="Ned" />
					</Slot>
					<Slot>
						<Job name="CutBeefToCutCosts" character="Krusty" />
					</Slot>
					<Slot>
						<Job name="SubstituteMothersPackedLunch" character="Skinner" />
					</Slot>
					<Slot>
						<Job name="EatVeggiesCompetitively" character="CBGuy" />
					</Slot>
					<Slot>
						<Job name="PreachHolyVeganism" character="Lovejoy" />
					</Slot>
				</ResourceGenerator>
			</JobList>
			<JobList name="AFT_JL_04">
				<Title value="QST_ThisThanksgivingsGoneToTheBirds_4_1_name" />
				<ResourceGenerator resourceCapSelector="__AFT_GameConfig:ResourceQuantities:ResourceList04__" slotsUnlockedVariable="Monorail_UnusedVariable" resourceName="AFT_ActivistBadges" resourceCapIcon="ico_mono15_junk_sm.rgb" topupConfig="AFT_Ratio" menuConfig="AFT_MenuConfig:ResourceGeneratorConfig">
					<Slot>
						<Job name="OptimizeTofunWithCONRAD" character="QuinnHopper" />
					</Slot>
					<Slot>
						<Job name="SubOutSpaghettiWithZucchini" character="Luigi" />
					</Slot>
					<Slot>
						<Job name="RegressTofunBugs" character="Lisa" skin="ProgrammerLisa" />
					</Slot>
					<Slot>
						<Job name="SubMeatWithGardenVeggies" character="Ned" />
					</Slot>
					<Slot>
						<Job name="CutBeefToCutCosts" character="Krusty" />
					</Slot>
					<Slot>
						<Job name="SubstituteMothersPackedLunch" character="Skinner" />
					</Slot>
					<Slot>
						<Job name="EatVeggiesCompetitively" character="CBGuy" />
					</Slot>
					<Slot>
						<Job name="PreachHolyVeganism" character="Lovejoy" />
					</Slot>
				</ResourceGenerator>
			</JobList>
			<JobList name="AFT_JL_05">
				<Title value="QST_ThisThanksgivingsGoneToTheBirds_5_1_name" />
				<ResourceGenerator resourceCapSelector="__AFT_GameConfig:ResourceQuantities:ResourceList05__" slotsUnlockedVariable="Monorail_UnusedVariable" resourceName="AFT_ActivistBadges" resourceCapIcon="ico_mono15_junk_sm.rgb" topupConfig="AFT_Ratio" menuConfig="AFT_MenuConfig:ResourceGeneratorConfig">
					<Slot>
						<Job name="OptimizeTofunWithCONRAD" character="QuinnHopper" />
					</Slot>
					<Slot>
						<Job name="SubOutSpaghettiWithZucchini" character="Luigi" />
					</Slot>
					<Slot>
						<Job name="RegressTofunBugs" character="Lisa" skin="ProgrammerLisa" />
					</Slot>
					<Slot>
						<Job name="SubMeatWithGardenVeggies" character="Ned" />
					</Slot>
					<Slot>
						<Job name="CutBeefToCutCosts" character="Krusty" />
					</Slot>
					<Slot>
						<Job name="SubstituteMothersPackedLunch" character="Skinner" />
					</Slot>
					<Slot>
						<Job name="EatVeggiesCompetitively" character="CBGuy" />
					</Slot>
					<Slot>
						<Job name="PreachHolyVeganism" character="Lovejoy" />
					</Slot>
				</ResourceGenerator>
			</JobList>
		</EventCurrencyJobLists>
		<Jobs override="true">
			<Job id="187031" name="SubstituteCafeteriaMysteryMeat">
				<Reward AFT_ActivistBadges="__AFT_GameConfig:CurrencyRewards:RegularJobReward__" xp="35" />
			</Job>
			<Job id="187030" name="SubOutSpaghettiWithZucchini">
				<Reward AFT_ActivistBadges="__AFT_GameConfig:CurrencyRewards:RegularJobReward__" xp="35" />
			</Job>
			<Job id="187032" name="RegressTofunBugs">
				<Reward AFT_ActivistBadges="__AFT_GameConfig:CurrencyRewards:RegularJobReward__" xp="35" />
			</Job>
			<Job id="187033" name="SubMeatWithGardenVeggies">
				<Reward AFT_ActivistBadges="__AFT_GameConfig:CurrencyRewards:RegularJobReward__" xp="35" />
			</Job>
			<Job id="187034" name="CutBeefToCutCosts">
				<Reward AFT_ActivistBadges="__AFT_GameConfig:CurrencyRewards:RegularJobReward__" xp="35" />
			</Job>
			<Job id="187035" name="SubstituteMothersPackedLunch">
				<Reward AFT_ActivistBadges="__AFT_GameConfig:CurrencyRewards:RegularJobReward__" xp="35" />
			</Job>
			<Job id="187036" name="EatVeggiesCompetitively">
				<Reward AFT_ActivistBadges="__AFT_GameConfig:CurrencyRewards:RegularJobReward__" xp="35" />
			</Job>
			<Job id="187037" name="PreachHolyVeganism">
				<Reward AFT_ActivistBadges="__AFT_GameConfig:CurrencyRewards:RegularJobReward__" xp="35" />
			</Job>
			<Job id="187038" name="OptimizeTofunWithCONRAD">
				<Reward AFT_ActivistBadges="__AFT_GameConfig:CurrencyRewards:PremiumJobReward__" xp="55" />
			</Job>
			<Job id="187101" name="ThisFryerRunsDeepWayDeep" time="4h" replaceTaxJob="true">
				<Reward AFT_ActivistBadges="__AFT_GameConfig:CurrencyRewards:DeucesCabooseTaxReward__" xp="10" />
			</Job>
		</Jobs>
		<Buildings override="true">
			<Building name="CONRAD">
				<BuildMenuText text="UI_CONRAD_ExcitingText" />
			</Building>
			<Building name="DeucesCabooseChiliDogs">
				<BuildMenuText text="UI_DeucesCabooseChiliDogs_ExcitingText" />
			</Building>
		</Buildings>
	</SpecialEvent>
	<SpecialEvent id="187001" name="AnimalFriendlyThanksgiving_Store">
		<Variable name="AFT_Store" value="false" />
	</SpecialEvent>
</SpecialEvents>