<Consumables>
	<MasterList>
		<DataID id="241900" name="LoveAndWar_LoveAndWarMysteryBox" />
		<DataID id="241901" name="LoveAndWarTokenForDozenDonuts" />
		<DataID id="241902" name="LoveAndWar_MysteryBoxTokenPurchase" />
		<DataID id="241903" name="LoveAndWar_MysteryBoxFiveTokensPurchase" />
	</MasterList>
	<ConsumableDefaults>
		<Subland value="Springfield" />
	</ConsumableDefaults>
	<Consumable id="241900" name="LoveAndWar_LoveAndWarMysteryBox" textpoolDesc="CON_MoesArk_TimeTravelingToaster_MysteryBox_desc" preview="true" type="PrizeBox" icon="ICO_STOR_Single_LoveAndWar_MysteryBox" attributes="LoveAndWar_GameConfig:LoveAndWarMysteryBox_MysteryBoxGeneralConfig">
		<VisibilityRequirements>
			<Requirement type="reqList" location="LoveAndWar_Requirements:LoveAndWarBox_Available" />
		</VisibilityRequirements>
		<Sell allowed="false" />
		<Cost LoveAndWarToken="__LoveAndWar_GameConfig:PremiumCosts:LoveAndWarMysteryBox__" />
		<Sublands>
			<Subland value="Springfield" />
		</Sublands>
		<BuildMenuText text="CON_MoesArk_TimeTravelingToaster_MysteryBox_desc" />
	</Consumable>
	<Consumable id="241901" name="LoveAndWarTokenForDozenDonuts" type="Script" autoconsume="true" icon="DonutBunch_00" textpoolName="CON_WinterWonderLandTokenForDozenDonuts_name">
		<VisibilityRequirements>
			<Requirement type="conditional" logic="OR">
				<Requirement type="time" start="LoveAndWar_End" />
				<Requirement type="reqList" location="LoveAndWar_Requirements:LoveAndWarBox_Available" not="true" />
			</Requirement>
		</VisibilityRequirements>
		<Cost LoveAndWarToken="1" />
		<Script name="LoveAndWar_Scripts:LoveAndWarTokenForDozenDonuts" />
	</Consumable>
	<Consumable id="241902" name="LoveAndWar_MysteryBoxTokenPurchase" type="Script" icon="ICO_STOR_MysteryBoxToken" textpoolName="UI_MysteryBoxToken" textpoolDesc="UI_LoveAndWar_MysteryBoxTokenSingular">
		<VisibilityRequirements>
			<Requirement type="reqList" location="LoveAndWar_Requirements:LoveAndWarBox_Available" />
		</VisibilityRequirements>
		<Sell allowed="false" />
		<Cost donuts="60" />
		<BuildMenuText text="UI_LoveAndWar_MysteryBoxTokenSingular" />
		<Script name="LoveAndWar_Scripts:RewardOneLoveAndWarToken_Store" />
	</Consumable>
	<Consumable id="241903" name="LoveAndWar_MysteryBoxFiveTokensPurchase" type="Script" icon="ICO_STOR_MysteryBoxToken" textpoolName="UI_MysteryBoxTokensFive" textpoolDesc="UI_LoveAndWar_MysteryBoxTokenPlural">
		<VisibilityRequirements>
			<Requirement type="reqList" location="LoveAndWar_Requirements:LoveAndWarBox_Available" />
		</VisibilityRequirements>
		<Sell allowed="false" />
		<Cost donuts="240" />
		<BuildMenuText text="UI_5Tokens_Best_Deal" />
		<Script name="LoveAndWar_Scripts:RewardFiveLoveAndWarTokens_Store" />
	</Consumable>
</Consumables>